{"population_total_2020":{"1":{"min":12461.0,"max":22240.0,"score":0.0,"description":"Total population in 2020"},"2":{"min":22257.0,"max":26345.0,"score":0.0,"description":"Total population in 2020"},"3":{"min":26378.0,"max":28580.0,"score":0.0,"description":"Total population in 2020"},"4":{"min":28744.0,"max":33835.0,"score":0.0,"description":"Total population in 2020"},"5":{"min":33935.0,"max":40227.0,"score":0.0,"description":"Total population in 2020"},"6":{"min":41036.0,"max":45372.0,"score":0.0,"description":"Total population in 2020"},"7":{"min":46873.0,"max":52893.0,"score":0.0,"description":""},"8":{"min":53255.0,"max":62577.0,"score":0.0,"description":"Total population in 2020"},"9":{"min":63089.0,"max":74368.0,"score":0.0,"description":"Total population in 2020"},"10":{"min":76957.0,"max":132483.0,"score":0.0,"description":"Total population in 2020"}},"population_total_2010":{"1":{"min":13225.0,"max":21907.0,"score":0.0,"description":"Total population in 2010"},"2":{"min":22009.0,"max":25349.0,"score":0.0,"description":"Total population in 2010"},"3":{"min":25393.0,"max":28484.0,"score":0.0,"description":"Total population in 2010"},"4":{"min":28531.0,"max":31919.0,"score":0.0,"description":"Total population in 2010"},"5":{"min":31993.0,"max":36579.0,"score":0.0,"description":"Total population in 2010"},"6":{"min":36834.0,"max":43832.0,"score":0.0,"description":"Total population in 2010"},"7":{"min":44000.0,"max":50994.0,"score":0.0,"description":"Total population in 2010"},"8":{"min":51180.0,"max":59990.0,"score":0.0,"description":"Total population in 2010"},"9":{"min":60499.0,"max":71364.0,"score":0.0,"description":"Total population in 2010"},"10":{"min":75055.0,"max":138076.0,"score":0.0,"description":"Total population in 2010"}},"delta_population":{"1":{"min":-0.17801807820797,"max":-0.0564504563808441,"score":0.0,"description":"Change in total population between 2010 and 2020"},"2":{"min":-0.0545139797031879,"max":-0.0262764561921358,"score":0.0,"description":"Change in total population between 2010 and 2020"},"3":{"min":-0.0262700077146292,"max":-0.00566144613549113,"score":0.0,"description":"Change in total population between 2010 and 2020"},"4":{"min":-0.00434978306293488,"max":0.0172229968011379,"score":0.0,"description":"Change in total population between 2010 and 2020"},"5":{"min":0.0185460727661848,"max":0.0373112671077251,"score":0.0,"description":"Change in total population between 2010 and 2020"},"6":{"min":0.0374613516032696,"max":0.0527007505297661,"score":0.0,"description":"Change in total population between 2010 and 2020"},"7":{"min":0.0545410588383675,"max":0.0763027891516685,"score":0.0,"description":"Change in total population between 2010 and 2020"},"8":{"min":0.0783445909619331,"max":0.102105207741261,"score":0.0,"description":"Change in total population between 2010 and 2020"},"9":{"min":0.104716464877129,"max":0.157627537846565,"score":0.0,"description":"Change in total population between 2010 and 2020"},"10":{"min":0.15848334133625,"max":0.43088710308075,"score":0.0,"description":"Change in total population between 2010 and 2020"}},"wavg_median_income_2020":{"1":{"min":25358.0,"max":34779.0,"score":0.0,"description":"Median income in 2020 (weighted average)"},"2":{"min":35444.0,"max":45947.0,"score":0.0,"description":"Median income in 2020 (weighted average)"},"3":{"min":48791.0,"max":56926.0,"score":0.0,"description":"Median income in 2020 (weighted average)"},"4":{"min":57201.0,"max":62620.0,"score":0.0,"description":"Median income in 2020 (weighted average)"},"5":{"min":62645.0,"max":68167.0,"score":0.0,"description":"Median income in 2020 (weighted average)"},"6":{"min":70431.0,"max":77582.0,"score":0.0,"description":"Median income in 2020 (weighted average)"},"7":{"min":77893.0,"max":85463.0,"score":0.0,"description":"Median income in 2020 (weighted average)"},"8":{"min":86011.0,"max":94923.0,"score":0.0,"description":"Median income in 2020 (weighted average)"},"9":{"min":95467.0,"max":118487.0,"score":0.0,"description":"Median income in 2020 (weighted average)"},"10":{"min":119389.0,"max":180811.0,"score":0.0,"description":"Median income in 2020 (weighted average)"}},"wavg_median_income_2010":{"1":{"min":19457.0,"max":27367.0,"score":0.0,"description":"Median income in 2010 (weighted average)"},"2":{"min":27638.0,"max":34517.0,"score":0.0,"description":"Median income in 2010 (weighted average)"},"3":{"min":34850.0,"max":40566.0,"score":0.0,"description":"Median income in 2010 (weighted average)"},"4":{"min":40664.0,"max":46328.0,"score":0.0,"description":"Median income in 2010 (weighted average)"},"5":{"min":46648.0,"max":53151.0,"score":0.0,"description":"Median income in 2010 (weighted average)"},"6":{"min":53265.0,"max":57074.0,"score":0.0,"description":"Median income in 2010 (weighted average)"},"7":{"min":57097.0,"max":64394.0,"score":0.0,"description":"Median income in 2010 (weighted average)"},"8":{"min":64957.0,"max":73738.0,"score":0.0,"description":"Median income in 2010 (weighted average)"},"9":{"min":73741.0,"max":87173.0,"score":0.0,"description":"Median income in 2010 (weighted average)"},"10":{"min":87367.0,"max":154185.0,"score":0.0,"description":"Median income in 2010 (weighted average)"}},"delta_median_income":{"1":{"min":-0.0664073526859283,"max":0.105483427643776,"score":0.0,"description":"Change in median income between 2010 and 2020"},"2":{"min":0.116432011127472,"max":0.186678603291512,"score":0.0,"description":"Change in median income between 2010 and 2020"},"3":{"min":0.186874404549599,"max":0.235837519168854,"score":0.0,"description":"Change in median income between 2010 and 2020"},"4":{"min":0.237721964716911,"max":0.265297681093216,"score":0.0,"description":"Change in median income between 2010 and 2020"},"5":{"min":0.266908556222916,"max":0.306129425764084,"score":0.0,"description":"Change in median income between 2010 and 2020"},"6":{"min":0.308128893375397,"max":0.350472301244736,"score":0.0,"description":"Change in median income between 2010 and 2020"},"7":{"min":0.350571155548096,"max":0.420642375946045,"score":0.0,"description":"Change in median income between 2010 and 2020"},"8":{"min":0.421560734510422,"max":0.534601092338562,"score":0.0,"description":"Change in median income between 2010 and 2020"},"9":{"min":0.551145195960999,"max":0.658313751220703,"score":0.0,"description":"Change in median income between 2010 and 2020"},"10":{"min":0.671615183353424,"max":1.68479955196381,"score":0.0,"description":"Change in median income between 2010 and 2020"}},"wavg_commute_time_2020":{"1":{"min":23.5,"max":32.9000015258789,"score":0.0,"description":"Average commuting time in 2020"},"2":{"min":33.0999984741211,"max":38.4000015258789,"score":0.0,"description":"Average commuting time in 2020"},"3":{"min":39.0,"max":41.5999984741211,"score":0.0,"description":"Average commuting time in 2020"},"4":{"min":41.7000007629395,"max":42.7999992370605,"score":0.0,"description":"Average commuting time in 2020"},"5":{"min":42.7999992370605,"max":43.9000015258789,"score":0.0,"description":"Average commuting time in 2020"},"6":{"min":44.0,"max":44.9000015258789,"score":0.0,"description":"Average commuting time in 2020"},"7":{"min":45.0,"max":45.9000015258789,"score":0.0,"description":"Average commuting time in 2020"},"8":{"min":45.9000015258789,"max":47.0999984741211,"score":0.0,"description":"Average commuting time in 2020"},"9":{"min":47.2000007629395,"max":48.4000015258789,"score":0.0,"description":"Average commuting time in 2020"},"10":{"min":48.5,"max":54.0,"score":0.0,"description":"Average commuting time in 2020"}},"wavg_commute_time_2010":{"1":{"min":21.6000003814697,"max":31.2999992370605,"score":0.0,"description":"Average commuting time in 2010"},"2":{"min":32.2000007629395,"max":36.2000007629395,"score":0.0,"description":"Average commuting time in 2010"},"3":{"min":36.2999992370605,"max":38.0999984741211,"score":0.0,"description":"Average commuting time in 2010"},"4":{"min":38.0999984741211,"max":39.5,"score":0.0,"description":"Average commuting time in 2010"},"5":{"min":39.7000007629395,"max":41.2000007629395,"score":0.0,"description":"Average commuting time in 2010"},"6":{"min":41.2000007629395,"max":41.9000015258789,"score":0.0,"description":"Average commuting time in 2010"},"7":{"min":41.9000015258789,"max":43.5999984741211,"score":0.0,"description":"Average commuting time in 2010"},"8":{"min":43.7000007629395,"max":44.5,"score":0.0,"description":"Average commuting time in 2010"},"9":{"min":44.5,"max":46.4000015258789,"score":0.0,"description":"Average commuting time in 2010"},"10":{"min":46.5,"max":53.5,"score":0.0,"description":"Average commuting time in 2010"}},"delta_commute_time":{"1":{"min":-0.14579439163208,"max":-0.0127795534208417,"score":0.0,"description":"Change in commuting time between 2010 and 2020"},"2":{"min":-0.0109090907499194,"max":0.0129533680155873,"score":0.0,"description":"Change in commuting time between 2010 and 2020"},"3":{"min":0.0137457037344575,"max":0.0314769968390465,"score":0.0,"description":"Change in commuting time between 2010 and 2020"},"4":{"min":0.0318471342325211,"max":0.0409482754766941,"score":0.0,"description":"Change in commuting time between 2010 and 2020"},"5":{"min":0.0410022772848606,"max":0.0621301792562008,"score":0.0,"description":"Change in commuting time between 2010 and 2020"},"6":{"min":0.0623306222259998,"max":0.0725806429982185,"score":0.0,"description":"Change in commuting time between 2010 and 2020"},"7":{"min":0.077294684946537,"max":0.0912863090634346,"score":0.0,"description":"Change in commuting time between 2010 and 2020"},"8":{"min":0.0916442051529884,"max":0.115492954850197,"score":0.0,"description":"Change in commuting time between 2010 and 2020"},"9":{"min":0.117021277546883,"max":0.137681156396866,"score":0.0,"description":"Change in commuting time between 2010 and 2020"},"10":{"min":0.140877604484558,"max":0.264705896377563,"score":0.0,"description":"Change in commuting time between 2010 and 2020"}},"wavg_unemployment_rate_2020":{"1":{"min":2.09999990463257,"max":3.79999995231628,"score":0.0,"description":"Average unememplyment rate in 2020"},"2":{"min":3.79999995231628,"max":4.59999990463257,"score":0.0,"description":"Average unememplyment rate in 2020"},"3":{"min":4.69999980926514,"max":5.09999990463257,"score":0.0,"description":"Average unememplyment rate in 2020"},"4":{"min":5.19999980926514,"max":5.59999990463257,"score":0.0,"description":"Average unememplyment rate in 2020"},"5":{"min":5.59999990463257,"max":6.09999990463257,"score":0.0,"description":"Average unememplyment rate in 2020"},"6":{"min":6.09999990463257,"max":6.80000019073486,"score":0.0,"description":"Average unememplyment rate in 2020"},"7":{"min":6.80000019073486,"max":7.69999980926514,"score":0.0,"description":"Average unememplyment rate in 2020"},"8":{"min":7.69999980926514,"max":8.69999980926514,"score":0.0,"description":"Average unememplyment rate in 2020"},"9":{"min":8.80000019073486,"max":11.3000001907349,"score":0.0,"description":"Average unememplyment rate in 2020"},"10":{"min":11.3000001907349,"max":20.1000003814697,"score":0.0,"description":"Average unememplyment rate in 2020"}},"wavg_unemployment_rate_2010":{"1":{"min":3.59999990463257,"max":5.40000009536743,"score":0.0,"description":"Average unemployment rate in 2010"},"2":{"min":5.5,"max":6.19999980926514,"score":0.0,"description":"Average unemployment rate in 2010"},"3":{"min":6.30000019073486,"max":6.80000019073486,"score":0.0,"description":"Average unemployment rate in 2010"},"4":{"min":6.90000009536743,"max":7.30000019073486,"score":0.0,"description":"Average unemployment rate in 2010"},"5":{"min":7.40000009536743,"max":8.19999980926514,"score":0.0,"description":"Average unemployment rate in 2010"},"6":{"min":8.19999980926514,"max":9.0,"score":0.0,"description":"Average unemployment rate in 2010"},"7":{"min":9.10000038146973,"max":10.1000003814697,"score":0.0,"description":"Average unemployment rate in 2010"},"8":{"min":10.1999998092651,"max":11.6000003814697,"score":0.0,"description":"Average unemployment rate in 2010"},"9":{"min":11.6999998092651,"max":13.8999996185303,"score":0.0,"description":"Average unemployment rate in 2010"},"10":{"min":14.3999996185303,"max":20.2999992370605,"score":0.0,"description":"Average unemployment rate in 2010"}},"delta_unemployment_rate":{"1":{"min":-0.588235318660736,"max":-0.470588237047195,"score":0.0,"description":"Change in unemployment rate between 2010 and 2020"},"2":{"min":-0.464566916227341,"max":-0.37007874250412,"score":0.0,"description":"Change in unemployment rate between 2010 and 2020"},"3":{"min":-0.369318187236786,"max":-0.325301200151443,"score":0.0,"description":"Change in unemployment rate between 2010 and 2020"},"4":{"min":-0.320754706859589,"max":-0.284768223762512,"score":0.0,"description":"Change in unemployment rate between 2010 and 2020"},"5":{"min":-0.283582091331482,"max":-0.246913582086563,"score":0.0,"description":"Change in unemployment rate between 2010 and 2020"},"6":{"min":-0.246575340628624,"max":-0.197278916835785,"score":0.0,"description":"Change in unemployment rate between 2010 and 2020"},"7":{"min":-0.197183102369308,"max":-0.147058829665184,"score":0.0,"description":"Change in unemployment rate between 2010 and 2020"},"8":{"min":-0.141732290387154,"max":-0.0714285746216774,"score":0.0,"description":"Change in unemployment rate between 2010 and 2020"},"9":{"min":-0.0645161271095276,"max":0.0299999993294477,"score":0.0,"description":"Change in unemployment rate between 2010 and 2020"},"10":{"min":0.0555555559694767,"max":0.331125825643539,"score":0.0,"description":"Change in unemployment rate between 2010 and 2020"}},"wavg_median_hcosts_2020":{"1":{"min":750.0,"max":1156.0,"score":0.0,"description":"Median housing costs in 2020 (weighted average)"},"2":{"min":1158.0,"max":1294.0,"score":0.0,"description":"Median housing costs in 2020 (weighted average)"},"3":{"min":1302.0,"max":1449.0,"score":0.0,"description":"Median housing costs in 2020 (weighted average)"},"4":{"min":1453.0,"max":1522.0,"score":0.0,"description":"Median housing costs in 2020 (weighted average)"},"5":{"min":1523.0,"max":1579.0,"score":0.0,"description":"Median housing costs in 2020 (weighted average)"},"6":{"min":1583.0,"max":1629.0,"score":0.0,"description":"Median housing costs in 2020 (weighted average)"},"7":{"min":1636.0,"max":1753.0,"score":0.0,"description":"Median housing costs in 2020 (weighted average)"},"8":{"min":1755.0,"max":1921.0,"score":0.0,"description":"Median housing costs in 2020 (weighted average)"},"9":{"min":1948.0,"max":2187.0,"score":0.0,"description":"Median housing costs in 2020 (weighted average)"},"10":{"min":2224.0,"max":3132.0,"score":0.0,"description":"Median housing costs in 2020 (weighted average)"}},"wavg_median_hcosts_2010":{"1":{"min":606.0,"max":860.0,"score":0.0,"description":"Median housing costs in 2010 (weighted average)"},"2":{"min":867.0,"max":959.0,"score":0.0,"description":"Median housing costs in 2010 (weighted average)"},"3":{"min":962.0,"max":1047.0,"score":0.0,"description":"Median housing costs in 2010 (weighted average)"},"4":{"min":1048.0,"max":1157.0,"score":0.0,"description":"Median housing costs in 2010 (weighted average)"},"5":{"min":1158.0,"max":1217.0,"score":0.0,"description":"Median housing costs in 2010 (weighted average)"},"6":{"min":1228.0,"max":1283.0,"score":0.0,"description":"Median housing costs in 2010 (weighted average)"},"7":{"min":1289.0,"max":1378.0,"score":0.0,"description":"Median housing costs in 2010 (weighted average)"},"8":{"min":1406.0,"max":1513.0,"score":0.0,"description":"Median housing costs in 2010 (weighted average)"},"9":{"min":1521.0,"max":1796.0,"score":0.0,"description":"Median housing costs in 2010 (weighted average)"},"10":{"min":1799.0,"max":2454.0,"score":0.0,"description":"Median housing costs in 2010 (weighted average)"}},"delta_median_hcosts":{"1":{"min":-0.0820073410868645,"max":0.118050791323185,"score":0.0,"description":"Change in housing costs between 2010 and 2020"},"2":{"min":0.121517769992352,"max":0.177852347493172,"score":0.0,"description":"Change in housing costs between 2010 and 2020"},"3":{"min":0.180666670203209,"max":0.234433963894844,"score":0.0,"description":"Change in housing costs between 2010 and 2020"},"4":{"min":0.245736435055733,"max":0.268605649471283,"score":0.0,"description":"Change in housing costs between 2010 and 2020"},"5":{"min":0.272497892379761,"max":0.300518125295639,"score":0.0,"description":"Change in housing costs between 2010 and 2020"},"6":{"min":0.301277220249176,"max":0.325557798147202,"score":0.0,"description":"Change in housing costs between 2010 and 2020"},"7":{"min":0.330827057361603,"max":0.353965193033218,"score":0.0,"description":"Change in housing costs between 2010 and 2020"},"8":{"min":0.357695609331131,"max":0.405814647674561,"score":0.0,"description":"Change in housing costs between 2010 and 2020"},"9":{"min":0.410356342792511,"max":0.544176697731018,"score":0.0,"description":"Change in housing costs between 2010 and 2020"},"10":{"min":0.555555582046509,"max":1.15807557106018,"score":0.0,"description":"Change in housing costs between 2010 and 2020"}},"b_apartments":{"1":{"min":2.0,"max":143.0,"score":-1.047773,"description":"Raw number of apartment buildings"},"2":{"min":143.0,"max":271.0,"score":-0.246392,"description":"Raw number of apartment buildings"},"3":{"min":285.0,"max":437.0,"score":-0.246392,"description":"Raw number of apartment buildings"},"4":{"min":438.0,"max":590.0,"score":-0.246392,"description":"Raw number of apartment buildings"},"5":{"min":590.0,"max":763.0,"score":0.041393,"description":"Raw number of apartment buildings"},"6":{"min":766.0,"max":948.0,"score":0.041393,"description":"Raw number of apartment buildings"},"7":{"min":966.0,"max":1149.0,"score":0.041393,"description":"Raw number of apartment buildings"},"8":{"min":1154.0,"max":1528.0,"score":0.375904,"description":"Raw number of apartment buildings"},"9":{"min":1711.0,"max":2315.0,"score":0.405459,"description":"Raw number of apartment buildings"},"10":{"min":2463.0,"max":4693.0,"score":-0.221849,"description":"Raw number of apartment buildings"}},"r_apartments":{"1":{"min":0.0890908315777779,"max":4.71604776382446,"score":-1.047773,"description":"Apartment buildings per 1000 people"},"2":{"min":4.97934103012085,"max":9.23126888275146,"score":0.041393,"description":"Apartment buildings per 1000 people"},"3":{"min":9.31754302978516,"max":11.241681098938,"score":-0.246392,"description":"Apartment buildings per 1000 people"},"4":{"min":11.2961492538452,"max":14.3398199081421,"score":0.041393,"description":"Apartment buildings per 1000 people"},"5":{"min":14.4032545089722,"max":17.7605857849121,"score":-1.047773,"description":"Apartment buildings per 1000 people"},"6":{"min":17.9956512451172,"max":21.5112857818604,"score":0.230133,"description":"Apartment buildings per 1000 people"},"7":{"min":21.5410442352295,"max":27.1204166412354,"score":0.041393,"description":"Apartment buildings per 1000 people"},"8":{"min":27.4349231719971,"max":33.580192565918,"score":0.041393,"description":"Apartment buildings per 1000 people"},"9":{"min":33.8588485717773,"max":43.5456466674805,"score":0.405459,"description":"Apartment buildings per 1000 people"},"10":{"min":43.8659553527832,"max":86.6591339111328,"score":0.067406,"description":"Apartment buildings per 1000 people"}},"b_dwellings":{"1":{"min":0.0,"max":88.0,"score":0.041393,"description":"Raw number of dwellings (single or two-family residential buldings)"},"2":{"min":110.0,"max":367.0,"score":-0.246392,"description":"Raw number of dwellings (single or two-family residential buldings)"},"3":{"min":368.0,"max":699.0,"score":0.498213,"description":"Raw number of dwellings (single or two-family residential buldings)"},"4":{"min":729.0,"max":1527.0,"score":0.230133,"description":"Raw number of dwellings (single or two-family residential buldings)"},"5":{"min":1544.0,"max":2391.0,"score":0.230133,"description":"Raw number of dwellings (single or two-family residential buldings)"},"6":{"min":2439.0,"max":3531.0,"score":-0.246392,"description":"Raw number of dwellings (single or two-family residential buldings)"},"7":{"min":3582.0,"max":4097.0,"score":0.041393,"description":"Raw number of dwellings (single or two-family residential buldings)"},"8":{"min":4223.0,"max":5290.0,"score":-1.047773,"description":"Raw number of dwellings (single or two-family residential buldings)"},"9":{"min":5306.0,"max":6697.0,"score":-0.221849,"description":"Raw number of dwellings (single or two-family residential buldings)"},"10":{"min":6857.0,"max":12839.0,"score":-1.024543,"description":"Raw number of dwellings (single or two-family residential buldings)"}},"r_dwellings":{"1":{"min":0.0,"max":1.81919777393341,"score":0.230133,"description":"Dwellings per 1000 people"},"2":{"min":1.98251783847809,"max":8.94192409515381,"score":0.041393,"description":"Dwellings per 1000 people"},"3":{"min":8.95782566070557,"max":20.1555233001709,"score":0.375904,"description":"Dwellings per 1000 people"},"4":{"min":20.4497871398926,"max":33.066520690918,"score":0.230133,"description":"Dwellings per 1000 people"},"5":{"min":33.3775825500488,"max":54.7163505554199,"score":-0.246392,"description":"Dwellings per 1000 people"},"6":{"min":56.2681922912598,"max":82.6265029907227,"score":0.230133,"description":"Dwellings per 1000 people"},"7":{"min":83.6302795410156,"max":120.099220275879,"score":-0.246392,"description":"Dwellings per 1000 people"},"8":{"min":121.000450134277,"max":151.716323852539,"score":-0.246392,"description":"Dwellings per 1000 people"},"9":{"min":155.612442016602,"max":211.297027587891,"score":-1.024543,"description":"Dwellings per 1000 people"},"10":{"min":213.513610839844,"max":286.633728027344,"score":-1.024543,"description":"Dwellings per 1000 people"}},"b_offices":{"1":{"min":0.0,"max":7.0,"score":-0.246392,"description":"Raw number of office buildings"},"2":{"min":7.0,"max":10.0,"score":0.230133,"description":"Raw number of office buildings"},"3":{"min":10.0,"max":13.0,"score":-0.246392,"description":"Raw number of office buildings"},"4":{"min":13.0,"max":17.0,"score":0.041393,"description":"Raw number of office buildings"},"5":{"min":17.0,"max":22.0,"score":0.041393,"description":"Raw number of office buildings"},"6":{"min":22.0,"max":29.0,"score":0.041393,"description":"Raw number of office buildings"},"7":{"min":30.0,"max":37.0,"score":-1.047773,"description":"Raw number of office buildings"},"8":{"min":37.0,"max":52.0,"score":-1.047773,"description":"Raw number of office buildings"},"9":{"min":54.0,"max":73.0,"score":0.067406,"description":"Raw number of office buildings"},"10":{"min":73.0,"max":768.0,"score":0.529928,"description":"Raw number of office buildings"}},"r_offices":{"1":{"min":0.0,"max":0.164590984582901,"score":-0.246392,"description":"Office buildings per 1000 people"},"2":{"min":0.164750456809998,"max":0.249046623706818,"score":0.230133,"description":"Office buildings per 1000 people"},"3":{"min":0.249981254339218,"max":0.343431860208511,"score":0.041393,"description":"Office buildings per 1000 people"},"4":{"min":0.349965006113052,"max":0.419689416885376,"score":0.041393,"description":"Office buildings per 1000 people"},"5":{"min":0.430378079414368,"max":0.556162476539612,"score":0.041393,"description":"Office buildings per 1000 people"},"6":{"min":0.56333327293396,"max":0.732311844825745,"score":-0.246392,"description":"Office buildings per 1000 people"},"7":{"min":0.763186156749725,"max":0.924484252929688,"score":-1.047773,"description":"Office buildings per 1000 people"},"8":{"min":0.932667434215546,"max":1.28738367557526,"score":-0.246392,"description":"Office buildings per 1000 people"},"9":{"min":1.2926641702652,"max":1.88258922100067,"score":0.257805,"description":"Office buildings per 1000 people"},"10":{"min":1.89767169952393,"max":27.6229190826416,"score":0.257805,"description":"Office buildings per 1000 people"}},"b_groceries":{"1":{"min":0.0,"max":1.0,"score":-0.246392,"description":"Raw number of grocery stores"},"2":{"min":1.0,"max":2.0,"score":-0.246392,"description":"Raw number of grocery stores"},"3":{"min":2.0,"max":3.0,"score":0.041393,"description":"Raw number of grocery stores"},"4":{"min":3.0,"max":4.0,"score":0.041393,"description":"Raw number of grocery stores"},"5":{"min":4.0,"max":5.0,"score":0.041393,"description":"Raw number of grocery stores"},"6":{"min":5.0,"max":7.0,"score":-0.246392,"description":"Raw number of grocery stores"},"7":{"min":7.0,"max":13.0,"score":-1.047773,"description":"Raw number of grocery stores"},"8":{"min":14.0,"max":22.0,"score":-0.246392,"description":"Raw number of grocery stores"},"9":{"min":22.0,"max":35.0,"score":0.257805,"description":"Raw number of grocery stores"},"10":{"min":35.0,"max":73.0,"score":0.529928,"description":"Raw number of grocery stores"}},"r_groceries":{"1":{"min":0.0,"max":0.0230049006640911,"score":-0.246392,"description":"Grocery stores per 1000 people"},"2":{"min":0.0254517681896687,"max":0.0465343557298183,"score":-0.246392,"description":"Grocery stores per 1000 people"},"3":{"min":0.0486570633947849,"max":0.0851081907749176,"score":0.041393,"description":"Grocery stores per 1000 people"},"4":{"min":0.0881600975990295,"max":0.10873955488205,"score":0.041393,"description":"Grocery stores per 1000 people"},"5":{"min":0.109270215034485,"max":0.14067417383194,"score":0.041393,"description":"Grocery stores per 1000 people"},"6":{"min":0.141232967376709,"max":0.197160884737968,"score":-0.246392,"description":"Grocery stores per 1000 people"},"7":{"min":0.198059022426605,"max":0.265372663736343,"score":-1.047773,"description":"Grocery stores per 1000 people"},"8":{"min":0.265996754169464,"max":0.396784573793411,"score":-0.246392,"description":"Grocery stores per 1000 people"},"9":{"min":0.398695170879364,"max":0.675858318805695,"score":0.529928,"description":"Grocery stores per 1000 people"},"10":{"min":0.701976835727692,"max":1.30423438549042,"score":0.257805,"description":"Grocery stores per 1000 people"}},"b_eatingdrinking":{"1":{"min":0.0,"max":4.0,"score":-1.047773,"description":"Raw number of eating-drinking places"},"2":{"min":4.0,"max":6.0,"score":0.375904,"description":"Raw number of eating-drinking places"},"3":{"min":6.0,"max":9.0,"score":-1.047773,"description":"Raw number of eating-drinking places"},"4":{"min":9.0,"max":13.0,"score":0.375904,"description":"Raw number of eating-drinking places"},"5":{"min":14.0,"max":19.0,"score":-0.246392,"description":"Raw number of eating-drinking places"},"6":{"min":19.0,"max":29.0,"score":-1.047773,"description":"Raw number of eating-drinking places"},"7":{"min":29.0,"max":49.0,"score":-1.047773,"description":"Raw number of eating-drinking places"},"8":{"min":50.0,"max":98.0,"score":-0.246392,"description":"Raw number of eating-drinking places"},"9":{"min":100.0,"max":178.0,"score":0.257805,"description":"Raw number of eating-drinking places"},"10":{"min":184.0,"max":693.0,"score":0.529928,"description":"Raw number of eating-drinking places"}},"r_eatingdrinking":{"1":{"min":0.0,"max":0.0803876966238022,"score":-1.047773,"description":"Eating-drinking places per 1000 people"},"2":{"min":0.0901794582605362,"max":0.190912559628487,"score":0.230133,"description":"Eating-drinking places per 1000 people"},"3":{"min":0.190978184342384,"max":0.261198908090591,"score":0.041393,"description":"Eating-drinking places per 1000 people"},"4":{"min":0.267272472381592,"max":0.374344885349274,"score":0.375904,"description":"Eating-drinking places per 1000 people"},"5":{"min":0.376253068447113,"max":0.50080394744873,"score":-1.047773,"description":"Eating-drinking places per 1000 people"},"6":{"min":0.502638876438141,"max":0.785335302352905,"score":-1.047773,"description":"Eating-drinking places per 1000 people"},"7":{"min":0.794506549835205,"max":1.1164036989212,"score":-1.047773,"description":"Eating-drinking places per 1000 people"},"8":{"min":1.18760633468628,"max":1.7339072227478,"score":-0.246392,"description":"Eating-drinking places per 1000 people"},"9":{"min":1.76600444316864,"max":3.51703095436096,"score":0.257805,"description":"Eating-drinking places per 1000 people"},"10":{"min":3.60224509239197,"max":24.9253673553467,"score":0.529928,"description":"Eating-drinking places per 1000 people"}},"b_hotels":{"1":{"min":0.0,"max":0.0,"score":-0.246392,"description":"Raw number of hotels"},"2":{"min":0.0,"max":0.0,"score":-0.246392,"description":"Raw number of hotels"},"3":{"min":0.0,"max":1.0,"score":-0.246392,"description":"Raw number of hotels"},"4":{"min":1.0,"max":1.0,"score":-0.246392,"description":"Raw number of hotels"},"5":{"min":1.0,"max":2.0,"score":0.375904,"description":"Raw number of hotels"},"6":{"min":2.0,"max":3.0,"score":-1.047773,"description":"Raw number of hotels"},"7":{"min":3.0,"max":4.0,"score":-0.246392,"description":"Raw number of hotels"},"8":{"min":4.0,"max":6.0,"score":0.041393,"description":"Raw number of hotels"},"9":{"min":6.0,"max":16.0,"score":0.067406,"description":"Raw number of hotels"},"10":{"min":16.0,"max":166.0,"score":0.529928,"description":"Raw number of hotels"}},"r_hotels":{"1":{"min":0.0,"max":0.0,"score":-0.246392,"description":"Hotels per 1000 people"},"2":{"min":0.0,"max":0.0,"score":-0.246392,"description":"Hotels per 1000 people"},"3":{"min":0.0,"max":0.0143494671210647,"score":-0.246392,"description":"Hotels per 1000 people"},"4":{"min":0.0146957254037261,"max":0.030664499849081,"score":0.230133,"description":"Hotels per 1000 people"},"5":{"min":0.0312431659549475,"max":0.042432215064764,"score":-0.246392,"description":"Hotels per 1000 people"},"6":{"min":0.0446907393634319,"max":0.0638311430811882,"score":0.041393,"description":"Hotels per 1000 people"},"7":{"min":0.0642776787281036,"max":0.0886976942420006,"score":-1.047773,"description":"Hotels per 1000 people"},"8":{"min":0.0902581363916397,"max":0.128228142857552,"score":0.041393,"description":"Hotels per 1000 people"},"9":{"min":0.138472184538841,"max":0.317021816968918,"score":0.257805,"description":"Hotels per 1000 people"},"10":{"min":0.319357633590698,"max":5.97057867050171,"score":0.405459,"description":"Hotels per 1000 people"}},"b_cinemas":{"1":{"min":0.0,"max":0.0,"score":-0.246392,"description":"Raw number of cinemas"},"2":{"min":0.0,"max":0.0,"score":-0.246392,"description":"Raw number of cinemas"},"3":{"min":0.0,"max":0.0,"score":0.375904,"description":"Raw number of cinemas"},"4":{"min":0.0,"max":0.0,"score":-0.246392,"description":"Raw number of cinemas"},"5":{"min":0.0,"max":0.0,"score":0.041393,"description":"Raw number of cinemas"},"6":{"min":0.0,"max":0.0,"score":-1.047773,"description":"Raw number of cinemas"},"7":{"min":0.0,"max":0.0,"score":0.041393,"description":"Raw number of cinemas"},"8":{"min":0.0,"max":1.0,"score":0.041393,"description":"Raw number of cinemas"},"9":{"min":1.0,"max":1.0,"score":-1.024543,"description":"Raw number of cinemas"},"10":{"min":1.0,"max":5.0,"score":0.529928,"description":"Raw number of cinemas"}},"r_cinemas":{"1":{"min":0.0,"max":0.0,"score":-0.246392,"description":"Cinemas per 1000 people"},"2":{"min":0.0,"max":0.0,"score":-0.246392,"description":"Cinemas per 1000 people"},"3":{"min":0.0,"max":0.0,"score":0.375904,"description":"Cinemas per 1000 people"},"4":{"min":0.0,"max":0.0,"score":-0.246392,"description":"Cinemas per 1000 people"},"5":{"min":0.0,"max":0.0,"score":0.041393,"description":"Cinemas per 1000 people"},"6":{"min":0.0,"max":0.0,"score":-1.047773,"description":"Cinemas per 1000 people"},"7":{"min":0.0,"max":0.0,"score":0.041393,"description":"Cinemas per 1000 people"},"8":{"min":0.0,"max":0.0126808611676097,"score":0.041393,"description":"Cinemas per 1000 people"},"9":{"min":0.0136849451810122,"max":0.0397258922457695,"score":-0.221849,"description":"Cinemas per 1000 people"},"10":{"min":0.0399648323655128,"max":0.179836705327034,"score":0.405459,"description":"Cinemas per 1000 people"}},"b_liveperf":{"1":{"min":0.0,"max":0.0,"score":0.041393,"description":"Raw number of buildings dedicated to host live performances"},"2":{"min":0.0,"max":0.0,"score":-1.047773,"description":"Raw number of buildings dedicated to host live performances"},"3":{"min":0.0,"max":0.0,"score":0.230133,"description":"Raw number of buildings dedicated to host live performances"},"4":{"min":0.0,"max":0.0,"score":0.041393,"description":"Raw number of buildings dedicated to host live performances"},"5":{"min":0.0,"max":0.0,"score":-0.246392,"description":"Raw number of buildings dedicated to host live performances"},"6":{"min":0.0,"max":0.0,"score":-0.246392,"description":"Raw number of buildings dedicated to host live performances"},"7":{"min":0.0,"max":1.0,"score":-0.246392,"description":"Raw number of buildings dedicated to host live performances"},"8":{"min":1.0,"max":2.0,"score":-0.246392,"description":"Raw number of buildings dedicated to host live performances"},"9":{"min":2.0,"max":3.0,"score":0.067406,"description":"Raw number of buildings dedicated to host live performances"},"10":{"min":4.0,"max":56.0,"score":0.529928,"description":"Raw number of buildings dedicated to host live performances"}},"r_liveperf":{"1":{"min":0.0,"max":0.0,"score":0.041393,"description":"Buildings dedicated to host live performances per 1000 people"},"2":{"min":0.0,"max":0.0,"score":-1.047773,"description":"Buildings dedicated to host live performances per 1000 people"},"3":{"min":0.0,"max":0.0,"score":0.230133,"description":"Buildings dedicated to host live performances per 1000 people"},"4":{"min":0.0,"max":0.0,"score":0.041393,"description":"Buildings dedicated to host live performances per 1000 people"},"5":{"min":0.0,"max":0.0,"score":-0.246392,"description":"Buildings dedicated to host live performances per 1000 people"},"6":{"min":0.0,"max":0.0,"score":-0.246392,"description":"Buildings dedicated to host live performances per 1000 people"},"7":{"min":0.0,"max":0.0190110448747873,"score":-1.047773,"description":"Buildings dedicated to host live performances per 1000 people"},"8":{"min":0.0191545207053423,"max":0.0363742187619209,"score":0.041393,"description":"Buildings dedicated to host live performances per 1000 people"},"9":{"min":0.0370144173502922,"max":0.0816782116889954,"score":0.067406,"description":"Buildings dedicated to host live performances per 1000 people"},"10":{"min":0.0847170427441597,"max":2.01417112350464,"score":0.529928,"description":"Buildings dedicated to host live performances per 1000 people"}},"b_manufacturing":{"1":{"min":0.0,"max":0.0,"score":-1.047773,"description":"Raw number of manufacturing buildings"},"2":{"min":0.0,"max":0.0,"score":-0.246392,"description":"Raw number of manufacturing buildings"},"3":{"min":0.0,"max":1.0,"score":-0.246392,"description":"Raw number of manufacturing buildings"},"4":{"min":1.0,"max":2.0,"score":0.041393,"description":"Raw number of manufacturing buildings"},"5":{"min":2.0,"max":3.0,"score":0.041393,"description":"Raw number of manufacturing buildings"},"6":{"min":3.0,"max":7.0,"score":0.041393,"description":"Raw number of manufacturing buildings"},"7":{"min":8.0,"max":11.0,"score":0.041393,"description":"Raw number of manufacturing buildings"},"8":{"min":12.0,"max":24.0,"score":0.230133,"description":"Raw number of manufacturing buildings"},"9":{"min":24.0,"max":49.0,"score":0.257805,"description":"Raw number of manufacturing buildings"},"10":{"min":51.0,"max":283.0,"score":0.067406,"description":"Raw number of manufacturing buildings"}},"r_manufacturing":{"1":{"min":0.0,"max":0.0,"score":-1.047773,"description":"Manufacturing buildings per 1000 people"},"2":{"min":0.0,"max":0.0,"score":-0.246392,"description":"Manufacturing buildings per 1000 people"},"3":{"min":0.0,"max":0.0189060922712088,"score":0.041393,"description":"Manufacturing buildings per 1000 people"},"4":{"min":0.0202876795083284,"max":0.0423585213720798,"score":-0.246392,"description":"Manufacturing buildings per 1000 people"},"5":{"min":0.0440800487995148,"max":0.0751103162765503,"score":0.041393,"description":"Manufacturing buildings per 1000 people"},"6":{"min":0.0765716359019279,"max":0.170216381549835,"score":-0.246392,"description":"Manufacturing buildings per 1000 people"},"7":{"min":0.172018349170685,"max":0.325827866792679,"score":0.375904,"description":"Manufacturing buildings per 1000 people"},"8":{"min":0.331656634807587,"max":0.575464308261871,"score":0.041393,"description":"Manufacturing buildings per 1000 people"},"9":{"min":0.580064117908478,"max":0.966888070106506,"score":0.405459,"description":"Manufacturing buildings per 1000 people"},"10":{"min":1.10170984268188,"max":10.5737752914429,"score":-0.221849,"description":"Manufacturing buildings per 1000 people"}},"b_warehouses":{"1":{"min":0.0,"max":0.0,"score":-1.047773,"description":"Raw number of warehouses"},"2":{"min":1.0,"max":2.0,"score":-0.246392,"description":"Raw number of warehouses"},"3":{"min":2.0,"max":4.0,"score":-0.246392,"description":"Raw number of warehouses"},"4":{"min":4.0,"max":6.0,"score":-1.047773,"description":"Raw number of warehouses"},"5":{"min":6.0,"max":8.0,"score":-0.246392,"description":"Raw number of warehouses"},"6":{"min":10.0,"max":16.0,"score":0.230133,"description":"Raw number of warehouses"},"7":{"min":16.0,"max":27.0,"score":0.606316,"description":"Raw number of warehouses"},"8":{"min":28.0,"max":47.0,"score":0.230133,"description":"Raw number of warehouses"},"9":{"min":47.0,"max":98.0,"score":0.067406,"description":"Raw number of warehouses"},"10":{"min":101.0,"max":448.0,"score":-0.221849,"description":"Raw number of warehouses"}},"r_warehouses":{"1":{"min":0.0,"max":0.0,"score":-1.047773,"description":"Warehouses per 1000 people"},"2":{"min":0.0112499855458736,"max":0.0447347238659859,"score":-0.246392,"description":"Warehouses per 1000 people"},"3":{"min":0.0452243126928806,"max":0.101442515850067,"score":-0.246392,"description":"Warehouses per 1000 people"},"4":{"min":0.101757004857063,"max":0.141232967376709,"score":-0.246392,"description":"Warehouses per 1000 people"},"5":{"min":0.14777597784996,"max":0.236089184880257,"score":-0.246392,"description":"Warehouses per 1000 people"},"6":{"min":0.246179819107056,"max":0.427925169467926,"score":0.230133,"description":"Warehouses per 1000 people"},"7":{"min":0.434273958206177,"max":0.621800303459167,"score":0.230133,"description":"Warehouses per 1000 people"},"8":{"min":0.633590042591095,"max":1.1172684431076,"score":0.705471,"description":"Warehouses per 1000 people"},"9":{"min":1.17230093479156,"max":1.88168001174927,"score":-1.024543,"description":"Warehouses per 1000 people"},"10":{"min":1.9453421831131,"max":9.28559970855713,"score":-0.221849,"description":"Warehouses per 1000 people"}},"b_childcare":{"1":{"min":1.0,"max":8.0,"score":-1.047773,"description":"Raw number of childcares"},"2":{"min":9.0,"max":10.0,"score":-1.047773,"description":"Raw number of childcares"},"3":{"min":10.0,"max":13.0,"score":0.230133,"description":"Raw number of childcares"},"4":{"min":13.0,"max":15.0,"score":0.375904,"description":"Raw number of childcares"},"5":{"min":15.0,"max":18.0,"score":-1.047773,"description":"Raw number of childcares"},"6":{"min":18.0,"max":21.0,"score":0.230133,"description":"Raw number of childcares"},"7":{"min":22.0,"max":25.0,"score":-1.047773,"description":"Raw number of childcares"},"8":{"min":25.0,"max":30.0,"score":0.498213,"description":"Raw number of childcares"},"9":{"min":30.0,"max":37.0,"score":-0.221849,"description":"Raw number of childcares"},"10":{"min":38.0,"max":131.0,"score":0.067406,"description":"Raw number of childcares"}},"r_childcare":{"1":{"min":0.0445454157888889,"max":0.273735105991364,"score":0.041393,"description":"Childcares per 1000 people"},"2":{"min":0.276115983724594,"max":0.328191667795181,"score":-0.246392,"description":"Childcares per 1000 people"},"3":{"min":0.33065801858902,"max":0.356774002313614,"score":-0.246392,"description":"Childcares per 1000 people"},"4":{"min":0.360673815011978,"max":0.395022720098495,"score":0.041393,"description":"Childcares per 1000 people"},"5":{"min":0.395768880844116,"max":0.431303560733795,"score":0.230133,"description":"Childcares per 1000 people"},"6":{"min":0.43561714887619,"max":0.489500224590302,"score":0.041393,"description":"Childcares per 1000 people"},"7":{"min":0.493772983551025,"max":0.536739826202393,"score":-0.246392,"description":"Childcares per 1000 people"},"8":{"min":0.536897838115692,"max":0.611528635025024,"score":-0.246392,"description":"Childcares per 1000 people"},"9":{"min":0.6124387383461,"max":0.75146210193634,"score":0.405459,"description":"Childcares per 1000 people"},"10":{"min":0.753958284854889,"max":1.31919479370117,"score":-0.221849,"description":"Childcares per 1000 people"}},"b_schoolsk12":{"1":{"min":0.0,"max":7.0,"score":-0.246392,"description":"Raw number of schools (K-12)"},"2":{"min":7.0,"max":9.0,"score":-1.047773,"description":"Raw number of schools (K-12)"},"3":{"min":9.0,"max":10.0,"score":0.041393,"description":"Raw number of schools (K-12)"},"4":{"min":10.0,"max":13.0,"score":-0.246392,"description":"Raw number of schools (K-12)"},"5":{"min":13.0,"max":15.0,"score":-1.047773,"description":"Raw number of schools (K-12)"},"6":{"min":15.0,"max":18.0,"score":0.230133,"description":"Raw number of schools (K-12)"},"7":{"min":18.0,"max":21.0,"score":0.041393,"description":"Raw number of schools (K-12)"},"8":{"min":22.0,"max":26.0,"score":0.041393,"description":"Raw number of schools (K-12)"},"9":{"min":26.0,"max":34.0,"score":0.529928,"description":"Raw number of schools (K-12)"},"10":{"min":36.0,"max":95.0,"score":0.067406,"description":"Raw number of schools (K-12)"}},"r_schoolsk12":{"1":{"min":0.0,"max":0.196467518806458,"score":0.041393,"description":"Schools (K-12) per 1000 people"},"2":{"min":0.197160884737968,"max":0.242296978831291,"score":0.041393,"description":"Schools (K-12) per 1000 people"},"3":{"min":0.244750112295151,"max":0.285311222076416,"score":-1.047773,"description":"Schools (K-12) per 1000 people"},"4":{"min":0.289249569177628,"max":0.330872982740402,"score":-0.246392,"description":"Schools (K-12) per 1000 people"},"5":{"min":0.330875396728516,"max":0.368444174528122,"score":-0.246392,"description":"Schools (K-12) per 1000 people"},"6":{"min":0.372134566307068,"max":0.415416568517685,"score":0.041393,"description":"Schools (K-12) per 1000 people"},"7":{"min":0.422004103660583,"max":0.478587627410889,"score":0.041393,"description":"Schools (K-12) per 1000 people"},"8":{"min":0.489236801862717,"max":0.581076264381409,"score":0.041393,"description":"Schools (K-12) per 1000 people"},"9":{"min":0.58828991651535,"max":0.675699710845947,"score":0.405459,"description":"Schools (K-12) per 1000 people"},"10":{"min":0.691110134124756,"max":1.1991126537323,"score":0.067406,"description":"Schools (K-12) per 1000 people"}},"b_hospitals":{"1":{"min":0.0,"max":0.0,"score":-1.047773,"description":"Raw number of hospitals"},"2":{"min":0.0,"max":1.0,"score":-0.246392,"description":"Raw number of hospitals"},"3":{"min":1.0,"max":2.0,"score":0.041393,"description":"Raw number of hospitals"},"4":{"min":2.0,"max":3.0,"score":-0.246392,"description":"Raw number of hospitals"},"5":{"min":3.0,"max":5.0,"score":0.041393,"description":"Raw number of hospitals"},"6":{"min":5.0,"max":6.0,"score":0.230133,"description":"Raw number of hospitals"},"7":{"min":6.0,"max":8.0,"score":-0.246392,"description":"Raw number of hospitals"},"8":{"min":8.0,"max":10.0,"score":0.230133,"description":"Raw number of hospitals"},"9":{"min":10.0,"max":15.0,"score":0.405459,"description":"Raw number of hospitals"},"10":{"min":15.0,"max":31.0,"score":-0.221849,"description":"Raw number of hospitals"}},"r_hospitals":{"1":{"min":0.0,"max":0.0,"score":-1.047773,"description":"Hospitals per 1000 people"},"2":{"min":0.0,"max":0.0399648323655128,"score":-0.246392,"description":"Hospitals per 1000 people"},"3":{"min":0.0403828285634518,"max":0.0566837191581726,"score":0.230133,"description":"Hospitals per 1000 people"},"4":{"min":0.0573394484817982,"max":0.0759157314896584,"score":-0.246392,"description":"Hospitals per 1000 people"},"5":{"min":0.0773290544748306,"max":0.10594342648983,"score":0.230133,"description":"Hospitals per 1000 people"},"6":{"min":0.106385238468647,"max":0.128555357456207,"score":-0.246392,"description":"Hospitals per 1000 people"},"7":{"min":0.134163349866867,"max":0.185987189412117,"score":0.230133,"description":"Hospitals per 1000 people"},"8":{"min":0.18611741065979,"max":0.239704683423042,"score":-0.246392,"description":"Hospitals per 1000 people"},"9":{"min":0.243688464164734,"max":0.345073491334915,"score":0.529928,"description":"Hospitals per 1000 people"},"10":{"min":0.355346083641052,"max":0.729873716831207,"score":-1.024543,"description":"Hospitals per 1000 people"}},"b_otherhealthcare":{"1":{"min":0.0,"max":0.0,"score":-0.246392,"description":"Raw number of healthcare facilities (non-hospitals)"},"2":{"min":0.0,"max":1.0,"score":-1.047773,"description":"Raw number of healthcare facilities (non-hospitals)"},"3":{"min":1.0,"max":3.0,"score":-1.047773,"description":"Raw number of healthcare facilities (non-hospitals)"},"4":{"min":3.0,"max":5.0,"score":0.041393,"description":"Raw number of healthcare facilities (non-hospitals)"},"5":{"min":5.0,"max":6.0,"score":-0.246392,"description":"Raw number of healthcare facilities (non-hospitals)"},"6":{"min":6.0,"max":8.0,"score":-0.246392,"description":"Raw number of healthcare facilities (non-hospitals)"},"7":{"min":8.0,"max":11.0,"score":0.230133,"description":"Raw number of healthcare facilities (non-hospitals)"},"8":{"min":11.0,"max":16.0,"score":0.230133,"description":"Raw number of healthcare facilities (non-hospitals)"},"9":{"min":16.0,"max":22.0,"score":0.405459,"description":"Raw number of healthcare facilities (non-hospitals)"},"10":{"min":22.0,"max":49.0,"score":0.257805,"description":"Raw number of healthcare facilities (non-hospitals)"}},"r_otherhealthcare":{"1":{"min":0.0,"max":0.0,"score":-0.246392,"description":"Healthcare facilities (non-hospitals) per 1000 people"},"2":{"min":0.0,"max":0.0361376106739044,"score":-1.047773,"description":"Healthcare facilities (non-hospitals) per 1000 people"},"3":{"min":0.0362778902053833,"max":0.0698015317320824,"score":-1.047773,"description":"Healthcare facilities (non-hospitals) per 1000 people"},"4":{"min":0.0719540938735008,"max":0.099990002810955,"score":0.230133,"description":"Healthcare facilities (non-hospitals) per 1000 people"},"5":{"min":0.101327389478683,"max":0.141849726438522,"score":-0.246392,"description":"Healthcare facilities (non-hospitals) per 1000 people"},"6":{"min":0.143414631485939,"max":0.186939179897308,"score":0.041393,"description":"Healthcare facilities (non-hospitals) per 1000 people"},"7":{"min":0.187024250626564,"max":0.240442410111427,"score":-0.246392,"description":"Healthcare facilities (non-hospitals) per 1000 people"},"8":{"min":0.240905806422234,"max":0.338702380657196,"score":0.230133,"description":"Healthcare facilities (non-hospitals) per 1000 people"},"9":{"min":0.345073491334915,"max":0.497884005308151,"score":0.257805,"description":"Healthcare facilities (non-hospitals) per 1000 people"},"10":{"min":0.502023756504059,"max":1.7623997926712,"score":0.405459,"description":"Healthcare facilities (non-hospitals) per 1000 people"}},"b_libraries":{"1":{"min":0.0,"max":0.0,"score":0.041393,"description":"Raw number of libraries"},"2":{"min":0.0,"max":1.0,"score":0.041393,"description":"Raw number of libraries"},"3":{"min":1.0,"max":1.0,"score":0.041393,"description":"Raw number of libraries"},"4":{"min":1.0,"max":1.0,"score":0.041393,"description":"Raw number of libraries"},"5":{"min":1.0,"max":1.0,"score":0.041393,"description":"Raw number of libraries"},"6":{"min":1.0,"max":1.0,"score":-1.047773,"description":"Raw number of libraries"},"7":{"min":1.0,"max":2.0,"score":-0.246392,"description":"Raw number of libraries"},"8":{"min":2.0,"max":2.0,"score":0.041393,"description":"Raw number of libraries"},"9":{"min":2.0,"max":3.0,"score":0.405459,"description":"Raw number of libraries"},"10":{"min":3.0,"max":5.0,"score":-0.221849,"description":"Raw number of libraries"}},"r_libraries":{"1":{"min":0.0,"max":0.0,"score":0.041393,"description":"Libraries per 1000 people"},"2":{"min":0.0,"max":0.0136849451810122,"score":-0.246392,"description":"Libraries per 1000 people"},"3":{"min":0.014070238918066,"max":0.0190110448747873,"score":-0.246392,"description":"Libraries per 1000 people"},"4":{"min":0.0191131494939327,"max":0.0240084510296583,"score":0.230133,"description":"Libraries per 1000 people"},"5":{"min":0.0243688467890024,"max":0.028982987627387,"score":0.230133,"description":"Libraries per 1000 people"},"6":{"min":0.0293700136244297,"max":0.0326722636818886,"score":0.041393,"description":"Libraries per 1000 people"},"7":{"min":0.032979354262352,"max":0.0379103794693947,"score":0.041393,"description":"Libraries per 1000 people"},"8":{"min":0.0379578657448292,"max":0.0461190789937973,"score":0.041393,"description":"Libraries per 1000 people"},"9":{"min":0.0463520884513855,"max":0.0622616559267044,"score":-0.221849,"description":"Libraries per 1000 people"},"10":{"min":0.0636375173926353,"max":0.143869370222092,"score":-0.221849,"description":"Libraries per 1000 people"}},"b_culturalcenters":{"1":{"min":0.0,"max":0.0,"score":0.041393,"description":"Raw number of cultural centers"},"2":{"min":0.0,"max":1.0,"score":-0.246392,"description":"Raw number of cultural centers"},"3":{"min":1.0,"max":1.0,"score":-1.047773,"description":"Raw number of cultural centers"},"4":{"min":1.0,"max":2.0,"score":0.041393,"description":"Raw number of cultural centers"},"5":{"min":2.0,"max":3.0,"score":-0.246392,"description":"Raw number of cultural centers"},"6":{"min":3.0,"max":4.0,"score":0.230133,"description":"Raw number of cultural centers"},"7":{"min":4.0,"max":7.0,"score":-0.246392,"description":"Raw number of cultural centers"},"8":{"min":7.0,"max":15.0,"score":-1.047773,"description":"Raw number of cultural centers"},"9":{"min":15.0,"max":25.0,"score":0.067406,"description":"Raw number of cultural centers"},"10":{"min":28.0,"max":177.0,"score":0.64053,"description":"Raw number of cultural centers"}},"r_culturalcenters":{"1":{"min":0.0,"max":0.0,"score":0.041393,"description":"Cultura centers per 1000 people"},"2":{"min":0.0,"max":0.0256456285715103,"score":-0.246392,"description":"Cultura centers per 1000 people"},"3":{"min":0.028266154229641,"max":0.0379578657448292,"score":-0.246392,"description":"Cultura centers per 1000 people"},"4":{"min":0.0386645272374153,"max":0.0596395395696163,"score":0.041393,"description":"Cultura centers per 1000 people"},"5":{"min":0.0601196363568306,"max":0.0749925002455711,"score":0.375904,"description":"Cultura centers per 1000 people"},"6":{"min":0.0763553082942963,"max":0.0990049988031387,"score":-1.047773,"description":"Cultura centers per 1000 people"},"7":{"min":0.100914537906647,"max":0.161021947860718,"score":-1.047773,"description":"Cultura centers per 1000 people"},"8":{"min":0.162311315536499,"max":0.264092952013016,"score":-1.047773,"description":"Cultura centers per 1000 people"},"9":{"min":0.26816326379776,"max":0.556162476539612,"score":0.257805,"description":"Cultura centers per 1000 people"},"10":{"min":0.570112407207489,"max":6.36621952056885,"score":0.529928,"description":"Cultura centers per 1000 people"}},"b_worship":{"1":{"min":0.0,"max":8.0,"score":0.041393,"description":"Raw number of worship places"},"2":{"min":9.0,"max":12.0,"score":-1.047773,"description":"Raw number of worship places"},"3":{"min":12.0,"max":16.0,"score":-1.047773,"description":"Raw number of worship places"},"4":{"min":16.0,"max":18.0,"score":-0.246392,"description":"Raw number of worship places"},"5":{"min":19.0,"max":24.0,"score":0.041393,"description":"Raw number of worship places"},"6":{"min":24.0,"max":29.0,"score":0.375904,"description":"Raw number of worship places"},"7":{"min":30.0,"max":34.0,"score":0.041393,"description":"Raw number of worship places"},"8":{"min":34.0,"max":42.0,"score":-0.246392,"description":"Raw number of worship places"},"9":{"min":42.0,"max":55.0,"score":0.257805,"description":"Raw number of worship places"},"10":{"min":56.0,"max":211.0,"score":0.257805,"description":"Raw number of worship places"}},"r_worship":{"1":{"min":0.0,"max":0.246960490942001,"score":0.041393,"description":"Worship places per 1000 people"},"2":{"min":0.248547554016113,"max":0.330872982740402,"score":-0.246392,"description":"Worship places per 1000 people"},"3":{"min":0.33106005191803,"max":0.394321769475937,"score":-0.246392,"description":"Worship places per 1000 people"},"4":{"min":0.407028019428253,"max":0.467347949743271,"score":-0.246392,"description":"Worship places per 1000 people"},"5":{"min":0.470573484897614,"max":0.571755290031433,"score":0.041393,"description":"Worship places per 1000 people"},"6":{"min":0.5754674077034,"max":0.665232717990875,"score":0.041393,"description":"Worship places per 1000 people"},"7":{"min":0.666786372661591,"max":0.825320839881897,"score":0.041393,"description":"Worship places per 1000 people"},"8":{"min":0.833131790161133,"max":1.00708556175232,"score":-1.047773,"description":"Worship places per 1000 people"},"9":{"min":1.01299691200256,"max":1.23444592952728,"score":0.067406,"description":"Worship places per 1000 people"},"10":{"min":1.25225126743317,"max":2.41601467132568,"score":0.529928,"description":"Worship places per 1000 people"}}}